fatfs/esp32_wl.py
fatfs/partition_extended.py
fatfs/__init__.py
fatfs/wrapper.cpython-313-darwin.so
fatfs/diskio.py
fatfs_ng-0.1.15.dist-info/RECORD
fatfs_ng-0.1.15.dist-info/WHEEL
fatfs_ng-0.1.15.dist-info/top_level.txt
fatfs_ng-0.1.15.dist-info/METADATA
fatfs_ng-0.1.15.dist-info/licenses/LICENSE.md
