Metadata-Version: 2.4
Name: fatfs-ng
Version: 0.1.15
Summary: Enhanced Python wrapper around ChaN's FatFS library - Fork of fatfs-python with extended features.
Home-page: https://github.com/Jason2866/pyfatfs
Author: Johann Obermeier
Author-email: obermeier.johann@googlemail.com
Project-URL: Original Project, https://github.com/krakonos/fatfs-python
Project-URL: Bug Tracker, https://github.com/Jason2866/pyfatfs/issues
Project-URL: Documentation, https://github.com/Jason2866/pyfatfs
Keywords: fatfs fat filesystem embedded esp32 platformio
Classifier: Development Status :: 4 - Beta
Classifier: Intended Audience :: Developers
Classifier: Programming Language :: Python :: 3
Classifier: Programming Language :: Python :: 3.8
Classifier: Programming Language :: Python :: 3.9
Classifier: Programming Language :: Python :: 3.10
Classifier: Programming Language :: Python :: 3.11
Classifier: Programming Language :: Python :: 3.12
Classifier: Programming Language :: Python :: 3.13
Classifier: Programming Language :: Python :: 3.14
Classifier: Programming Language :: Cython
Classifier: License :: OSI Approved :: MIT License
Classifier: Operating System :: OS Independent
Classifier: Topic :: Scientific/Engineering
Classifier: Topic :: Software Development :: Embedded Systems
Classifier: Topic :: Software Development :: Libraries
Classifier: Topic :: System :: Filesystems
Requires-Python: >=3.8
License-File: LICENSE.md
Dynamic: author
Dynamic: author-email
Dynamic: classifier
Dynamic: description
Dynamic: description-content-type
Dynamic: home-page
Dynamic: keywords
Dynamic: license-file
Dynamic: project-url
Dynamic: requires-python
Dynamic: summary
